{
    "system": {"type": "spin","N": 20},
    "model": {"name": "custom_spin","params": {"N": 20,"d": 2,"dtype": "ComplexF64",
              "channels": [{"type": "FiniteRangeCoupling","op1": "X","op2": "X","range": 1,"strength": 1.0},
                           {"type": "FiniteRangeCoupling","op1": "Y","op2": "Y","range": 1,"strength": 1.0},
                           {"type": "FiniteRangeCoupling","op1": "Z","op2": "Z","range": 1,"strength": 2.0},
                           {"type": "Field","op": "Z","strength": 0.5}]}},
    "state": {"type": "random","params":{"bond_dim":5}},
    "algorithm": {"type": "dmrg","solver": {"type": "lanczos","krylov_dim": 4,"max_iter": 14},"options": {"chi_max": 40,"cutoff": 1e-8,"local_dim": 2},"run": {"n_sweeps": 50}},
    "description": "Quickstart example - XXZ model ground state search"
}


